jwt_auth/__init__.py
jwt_auth/auth.py
jwt_auth/dependencies.py
jwt_auth/exceptions.py
jwt_auth_provider-0.2.1.dist-info/METADATA
jwt_auth_provider-0.2.1.dist-info/WHEEL
jwt_auth_provider-0.2.1.dist-info/top_level.txt
jwt_auth_provider-0.2.1.dist-info/RECORD
