Metadata-Version: 2.1
Name: jwt-auth-provider
Version: 0.2.1
Summary: JWT authentication package for FastAPI
Home-page: https://github.com/Dhruv7201/auth
Author: Dhruv Modi
Author-email: dhruv.modi2345@gmail.com
License: UNKNOWN
Platform: UNKNOWN
Classifier: Programming Language :: Python :: 3
Classifier: Operating System :: OS Independent
Requires-Dist: fastapi
Requires-Dist: passlib
Requires-Dist: pyjwt
Requires-Dist: python-dotenv
